prybar.py
prybar-1.0.0.dist-info/LICENSE
prybar-1.0.0.dist-info/WHEEL
prybar-1.0.0.dist-info/METADATA
prybar-1.0.0.dist-info/RECORD
