Metadata-Version: 2.1
Name: prybar
Version: 1.0.0
Summary: Create temporary pkg_resources entry points at runtime.
Home-page: https://github.com/h4l/prybar
License: UNKNOWN
Author: Hal Blackburn
Author-email: hwtb2@cam.ac.uk
Requires-Python: ~=3.6
Classifier: License :: OSI Approved :: MIT License
Classifier: Programming Language :: Python :: 3 :: Only
Requires-Dist: flake8; extra == "dev"
Requires-Dist: sphinx; extra == "doc"
Requires-Dist: pytest; extra == "test"
Requires-Dist: pytest-cov; extra == "test"
Project-URL: Documentation, https://prybar.readthedocs.io/en/latest/
Provides-Extra: dev
Provides-Extra: doc
Provides-Extra: test
